LICENSE
quadrantic/__init__.py
quadrantic-0.1.0.dist-info/LICENSE
quadrantic-0.1.0.dist-info/WHEEL
quadrantic-0.1.0.dist-info/METADATA
quadrantic-0.1.0.dist-info/RECORD
