Metadata-Version: 2.1
Name: quadrantic
Version: 0.1.0
Summary: Determination of quadrants based on angle, coordinates and others
Home-page: https://github.com/earthobservations/quadrantic
License: MIT
Keywords: open-source,quadrant,geometry,plane-geometry,point,coordinates
Author: Benjamin Gutzmann
Author-email: gutzemann@gmail.com
Requires-Python: >=3.8,<4.0
Classifier: Development Status :: 4 - Beta
Classifier: Intended Audience :: Developers
Classifier: Intended Audience :: Education
Classifier: Intended Audience :: Information Technology
Classifier: Intended Audience :: Science/Research
Classifier: License :: OSI Approved :: MIT License
Classifier: Operating System :: MacOS
Classifier: Operating System :: POSIX
Classifier: Operating System :: Unix
Classifier: Programming Language :: Python
Classifier: Programming Language :: Python :: 3
Classifier: Programming Language :: Python :: 3.8
Classifier: Programming Language :: Python :: 3.9
Classifier: Programming Language :: Python :: 3.10
Classifier: Programming Language :: Python :: 3
Classifier: Programming Language :: Python :: 3.10
Classifier: Programming Language :: Python :: 3.8
Classifier: Programming Language :: Python :: 3.9
Classifier: Topic :: Scientific/Engineering :: Information Analysis
Classifier: Topic :: Scientific/Engineering :: Visualization
Classifier: Topic :: Software Development :: Libraries
Classifier: Topic :: Utilities
Requires-Dist: Shapely (>=1.8.4,<2.0.0)
Requires-Dist: matplotlib (>=3.6.0,<4.0.0)
Project-URL: Issues, https://github.com/earthobservations/quadrantic/issues
Project-URL: Repository, https://github.com/earthobservations/quadrantic
Project-URL: Releases, https://github.com/earthobservations/quadrantic/releases
